seKM/KeyManagerVault.py
seKM/Utilities.py
seKM/Vault.py
seKM/__about__.py
seKM/__init__.py
sekm-2025.6.0.dist-info/METADATA
sekm-2025.6.0.dist-info/WHEEL
sekm-2025.6.0.dist-info/top_level.txt
sekm-2025.6.0.dist-info/RECORD
