Metadata-Version: 2.4
Name: seKM
Version: 2025.6.0
Summary: seKM is a secure key management system
Author-email: Cybernetic Innovations <github@cyberneticinnovations.com>
License: MIT License
Classifier: License :: OSI Approved :: MIT License
Requires-Python: >=3.10
Requires-Dist: urllib3~=2.4.0
Requires-Dist: bitflags~=1.1.3
Requires-Dist: seCore~=2025.6.0
